[
    {
        "mapId": 1,
        "name": "GTA VCS Map",
        "src": "/assets/maps/gtavcsmapclean.jpg",
        "copyright": "Rockstar Games",
        "copyrightlink": "https://www.rockstargames.com/"
    },
    {
        "mapId": 2,
        "name": "GTA LCS Map",
        "src": "/assets/maps/gtalcsmapclean.jpg",
        "copyright": "Rockstar Games",
        "copyrightlink": "https://www.rockstargames.com/"
    },
    {
        "mapId": 3,
        "name": "GTA CTW Map",
        "src": "/assets/maps/gtactwmapclean.webp",
        "copyright": "Rockstar Games",
        "copyrightlink": "https://www.rockstargames.com/"
    },
    {
        "mapId": 4,
        "name": "GTA V Map",
        "src": "/assets/maps/gtavmapclean.png",
        "copyright": "Rockstar Games",
        "copyrightlink": "https://www.rockstargames.com/"
    },
    {
        "mapId": 5,
        "name": "GTA IV Map",
        "src": "/assets/maps/gtaivmapclean.webp",
        "copyright": "Rockstar Games",
        "copyrightlink": "https://www.rockstargames.com/"
    },
    {
        "mapId": 6,
        "name": "GTA SA Map",
        "src": "/assets/maps/gtasamapclean.jpg",
        "copyright": "Rockstar Games",
        "copyrightlink": "https://www.rockstargames.com/"
    },
    {
        "mapId": 7,
        "name": "GTA VC Map",
        "src": "/assets/maps/gtavcmapclean.webp",
        "copyright": "Rockstar Games",
        "copyrightlink": "https://www.rockstargames.com/"
    },
    {
        "mapId": 8,
        "name": "GTA III Map",
        "src": "/assets/maps/gta3mapclean.webp",
        "copyright": "Rockstar Games",
        "copyrightlink": "https://www.rockstargames.com/"
    }
]